exostriker/__init__.py
exostriker/__main__.py
exostriker/compile_swift.py
exostriker/desktop_entry.py
exostriker/gui.py
exostriker/install_swift.sh
exostriker/__pycache__/__init__.cpython-310.pyc
exostriker/__pycache__/gui.cpython-310.pyc
exostriker/autosave/.keep
exostriker/datafiles/.keep
exostriker/datafiles/51Peg_ELODIE.dat
exostriker/datafiles/51Peg_HARPS.dat
exostriker/datafiles/WASP-6_post.dat
exostriker/datafiles/WASP-6_pre.dat
exostriker/datafiles/WASP-6b_harps.vels
exostriker/datafiles/WASP_6_lc.tran
exostriker/datafiles/WASP_6_lc_a.tran
exostriker/datafiles/WASP_6_lc_b.tran
exostriker/datafiles/WASP_6_lc_clean.tran
exostriker/datafiles/hip5364.vels
exostriker/datafiles/hip5364_crires.vels
exostriker/datafiles/hip88048.vels
exostriker/datafiles/hip88048_crires.vels
exostriker/datafiles/hip88048_sato12.vels
exostriker/lib/ES_settings.json
exostriker/lib/Jupyter_emb.py
exostriker/lib/RVBank_window.py
exostriker/lib/RVBank_window_old.py
exostriker/lib/TESS_pdc_window.py
exostriker/lib/__init__.py
exostriker/lib/act.py
exostriker/lib/activity_window.py
exostriker/lib/calculator.py
exostriker/lib/cornerplot_parameter_window.py
exostriker/lib/datafiles_window.py
exostriker/lib/detrend_window.py
exostriker/lib/doublespinbox.py
exostriker/lib/dynesty_patch.py
exostriker/lib/es.py
exostriker/lib/exochat.py
exostriker/lib/exochat_opt.py
exostriker/lib/figureoptions.py
exostriker/lib/gls.py
exostriker/lib/gui_groups.py
exostriker/lib/jac2astrocen.py
exostriker/lib/libswift.a
exostriker/lib/mlp.py
exostriker/lib/pg_hack.py
exostriker/lib/print_info_window.py
exostriker/lib/qso.py
exostriker/lib/run_mcmc_from_ses.py
exostriker/lib/run_ns_from_ses.py
exostriker/lib/rvs.py
exostriker/lib/rvs_window.py
exostriker/lib/scientificspin.py
exostriker/lib/stdout_pipe.py
exostriker/lib/symbols_window.py
exostriker/lib/tdt.py
exostriker/lib/terminal.py
exostriker/lib/tls_hack.py
exostriker/lib/tree_view_ext.py
exostriker/lib/worker.py
exostriker/lib/worker_old.py
exostriker-0.93.81.dist-info/licenses/LICENSE
exostriker-0.93.81.dist-info/METADATA
exostriker-0.93.81.dist-info/WHEEL
exostriker-0.93.81.dist-info/entry_points.txt
exostriker-0.93.81.dist-info/top_level.txt
exostriker-0.93.81.dist-info/RECORD
