Metadata-Version: 2.4
Name: exostriker
Version: 0.93.81
Summary: This is the 'Transit and Radial velocity Interactive Fitting tool for Orbital analysis and N-body simulations: The Exo-Striker'
Author-email: Trifon Trifonov <trifonov@mpia.de>, "Matheus J. Castro" <matheusdejesuscastro@gmail.com>
License: MIT License
Project-URL: homepage, https://exostriker-manual.readthedocs.io/
Project-URL: repository, https://github.com/3fon3fonov/exostriker
Project-URL: Bug Tracker, https://github.com/3fon3fonov/exostriker/issues
Classifier: Programming Language :: Python :: 3
Classifier: License :: OSI Approved :: MIT License
Classifier: Operating System :: OS Independent
Requires-Python: >=3.8
License-File: LICENSE
Requires-Dist: numpy>=1.21
Requires-Dist: scipy>=1.2.1
Requires-Dist: matplotlib>=3.3.1
Requires-Dist: formlayout==1.2.0
Requires-Dist: PyQt6
Requires-Dist: jupyter
Requires-Dist: jupyter-client
Requires-Dist: ipykernel
Requires-Dist: qtconsole
Requires-Dist: pathos>=0.2.5
Requires-Dist: celerite>=0.3.1
Requires-Dist: batman-package>=2.4.8
Requires-Dist: ttvfast>=0.3.0
Requires-Dist: wotan>=1.7
Requires-Dist: openai
Requires-Dist: desktop_file
Requires-Dist: astropy
Requires-Dist: Pillow
Requires-Dist: ninja
Requires-Dist: meson
Requires-Dist: colorama
Requires-Dist: pywin32; sys_platform == "win32"
Dynamic: license-file
